Metadata-Version: 2.1
Name: micropython-firebase-firestore
Version: 1.0.0
Summary: Firebase Firestore implementation for Micropython optimized for ESP32.
Home-page: https://github.com/WoolDoughnut310/micropython-firebase-firestore
Author: WoolDoughnut310
Author-email: wooldoughnutspi@outlook.com
License: UNKNOWN
Platform: UNKNOWN
